[
  {
    "style_id": 0,
    "title": "Overview",
    "view_name": "overview",
    "view_location": "/views/styles/overview.html",
    "mod_date": "14 September, 2015",    
    "keywords": [
      "overview"
    ], 
    "style_markdown": "# How to use angular-md"
  },
  {
    "style_id": 1,
    "title": "Colors",
    "view_name": "colors",
    "view_location": "/views/styles/colors.html",
    "mod_date": "14 September, 2015",
    "keywords": [
      "colors"
    ],
    "colors_greyscale": {
      "rx-white": {
        "name": "Primary White",
        "hex": "#ffffff",
        "class": "rx-white",
        "usage": "lorem ipsum."
      },
      "rx-lt-grey": {
        "name": "Light Grey",
        "hex": "#dadada",
        "class": "rx-lt-grey",
        "usage": "lorem ipsum."
      },
      "rx-md-grey": {
        "name": "Medium Grey",
        "hex": "#f5f5f5",
        "class": "rx-md-grey",
        "usage": "lorem ipsum."
      },
      "rx-dk-grey": {
        "name": "Dark Grey",
        "hex": "#58585a",
        "class": "rx-dk-grey",
        "usage": "Primarily used as our global text-color accross the site."
      }
    },
    "colors_indicator": {
      "rx-ind-red": {
        "name": "Alert Red",
        "hex": "#d95553",
        "class": "rx-ind-red",
        "usage": "lorem ipsum."
      },
      "rx-ind-yellow": {
        "name": "Warning Yellow",
        "hex": "#efad58",
        "class": "rx-ind-yellow",
        "usage": "lorem ipsum."
      },
      "rx-ind-green": {
        "name": "Success Green",
        "hex": "#007b34",
        "class": "rx-ind-green",
        "usage": "lorem ipsum."
      },
      "rx-ind-blue": {
        "name": "Info Blue",
        "hex": "#066cb6",
        "class": "rx-ind-blue",
        "usage": "Primarily used as our global text-color accross the site."
      }
    },
    "colors_other": {
      "rx-white": {
        "name": "Primary White",
        "hex": "#ffffff",
        "class": "rx-white",
        "usage": "lorem ipsum."
      },
      "rx-lt-grey": {
        "name": "Light Grey",
        "hex": "#dadada",
        "class": "rx-lt-grey",
        "usage": "lorem ipsum."
      },
      "rx-md-grey": {
        "name": "Medium Grey",
        "hex": "#f5f5f5",
        "class": "rx-md-grey",
        "usage": "lorem ipsum."
      },
      "rx-dk-grey": {
        "name": "Dark Grey",
        "hex": "#58585a",
        "class": "rx-dk-grey",
        "usage": "Primarily used as our global text-color accross the site."
      }
    },
    "colors_rexel": {
      "rx-white": {
        "name": "Primary White",
        "hex": "#ffffff",
        "class": "rx-white",
        "usage": "lorem ipsum."
      },
      "rx-lt-grey": {
        "name": "Light Grey",
        "hex": "#dadada",
        "class": "rx-lt-grey",
        "usage": "lorem ipsum."
      },
      "rx-md-grey": {
        "name": "Medium Grey",
        "hex": "#f5f5f5",
        "class": "rx-md-grey",
        "usage": "lorem ipsum."
      },
      "rx-dk-grey": {
        "name": "Dark Grey",
        "hex": "#58585a",
        "class": "rx-dk-grey",
        "usage": "Primarily used as our global text-color accross the site."
      }
    },
    "colors_hagemeyer": {
      "rx-white": {
        "name": "Primary White",
        "hex": "#ffffff",
        "class": "rx-white",
        "usage": "lorem ipsum."
      },
      "rx-lt-grey": {
        "name": "Light Grey",
        "hex": "#dadada",
        "class": "rx-lt-grey",
        "usage": "lorem ipsum."
      },
      "rx-md-grey": {
        "name": "Medium Grey",
        "hex": "#f5f5f5",
        "class": "rx-md-grey",
        "usage": "lorem ipsum."
      },
      "rx-dk-grey": {
        "name": "Dark Grey",
        "hex": "#58585a",
        "class": "rx-dk-grey",
        "usage": "Primarily used as our global text-color accross the site."
      }
    }
  },
  {
    "style_id": 2,
    "title": "Grid System",
    "view_name": "grid_system",
    "view_location": "/views/styles/grid_system.html",
    "mod_date": "14 September, 2015",
    "keywords": [
      "grid system",
      "rows",
      "columns",
      "containers",
      "padding",
      "margin",
      "fluid",
      "width"
    ]
  }, 
  {
    "style_id": 3,    
    "title": "Typography",
    "view_name": "typography",
    "view_location": "/views/styles/typography.html",
    "mod_date": "14 September, 2015",
    "keywords": [
      "typography",
      "type",
      "headings",
      "h1",
      "h2",
      "h3",
      "h4",
      "h5",
      "h6",
      "body copy",
      "small",
      "text",
      "paragraph",
      "bold",
      "italics",
      "fonts",
      "lato",
      "open sans",
      "font weight",
      "font size",
      "alignment",
      "text transform",
      "lists",
      "ul",
      "ol",
      "dl",
      "dt",
      "dd",
      "input",
      "links",
      "icons",
      "disabled",
      "enabled"
    ]
  },
  {
    "style_id": 4,
    "title": "Tables",
    "view_name": "tables",
    "view_location": "/views/styles/tables.html",
    "mod_date": "14 September, 2015",
    "keywords": [
      "tables",
      "columns",
      "rows",
      "data",
      "tbody",
      "striped",
      "th",
      "td",
      "tr",
      "cells"
    ]
  },
  {
    "style_id": 5,
    "title": "Forms",
    "view_name": "forms",
    "view_location": "/views/styles/forms.html",
    "mod_date": "14 September, 2015",
    "keywords": [
      "forms",
      "input",
      "textarea",
      "text area",
      "select",
      "form-control",
      "form-group",
      "submit",
      "placeholder",
      "labels",
      "radio",
      "checkbox",
      "options",
      "inline form",
      "text",
      "password",
      "datetime",
      "datetime-local",
      "date",
      "month",
      "time",
      "week",
      "number",
      "email",
      "url",
      "search",
      "tel",
      "color",
      "disabled",
      "enabled",
      "focus",
      "blur",
      "fieldset",
      "readonly",
      "validation",
      "icons",
      "success",
      "warning",
      "error",
      "size"
    ]
  },
  {
    "style_id": 6,    
    "title": "Buttons",
    "view_name": "buttons",
    "view_location": "/views/styles/buttons.html",
    "mod_date": "14 September, 2015",
    "keywords": [
      "buttons",
      "a",
      "link",
      "input",
      "btn",
      "btn-default",
      "btn-primary",
      "btn-white",
      "value",
      "button size",
      "large button",
      "default button",
      "small-button",
      "extra small button",
      "btn-block",
      "btn-expand",
      "disabled",
      "enabled",
      "active"
    ]
  },
  {
    "style_id": 7,
    "title": "Images",
    "view_name": "images",
    "view_location": "/views/styles/images.html",
    "mod_date": "14 September, 2015",
    "keywords": [
      "images",
      "responsive images",
      "slideshows",
      "zoom",
      "img",
      "thumbnails"
    ]
  },
  {
    "style_id": 8,
    "title": "Helper Classes",
    "view_name": "helper_classes",
    "view_location": "/views/styles/helper_classes.html",
    "mod_date": "14 September, 2015",
    "keywords": [
      "helper classes",
      "text color",
      "muted",
      "primary",
      "success",
      "info",
      "warning",
      "danger",
      "contextual",
      "icons",
      "close",
      "floats",
      "center alignment",
      "clearfix",
      "show",
      "hide",
      "aria",
      "screen reader",
      "image replacement",
      "hidden text"
    ]
  },
  {
    "style_id": 9,    
    "title": "Responsive Utilities",
    "view_name": "responsive_utilities",
    "view_location": "/views/styles/responsive_utilities.html",
    "mod_date": "14 September, 2015",
    "keywords": [
      "responsive utilities",
      "visibility",
      "hidden",
      "display",
      "block",
      "inline-block",
      "inline",
      "print"
    ]
  },
  {
    "style_id": 10,
    "title": "Dropdowns",
    "view_name": "dropdowns",
    "view_location": "/views/styles/dropdowns.html",
    "mod_date": "14 September, 2015",
    "keywords": [
      "dropdowns",
      "toggle",
      "plugins",
      "menu",
      "divider",
      "disabled",
      "enabled",
      "mobile",
      "fly-in",
      "popup"
    ]
  },
  {
    "style_id": 11,
    "title": "Breadcrumbs",
    "view_name": "breadcrumbs",
    "view_location": "/views/styles/breadcrumbs.html",
    "mod_date": "14 September, 2015",
    "keywords": [
      "breadcrumbs",
      "path",
      "hierarchy"
    ]
  },
  {
    "style_id": 12,    
    "title": "Pagination",
    "view_name": "pagination",
    "view_location": "/views/styles/pagination.html",
    "mod_date": "14 September, 2015",
    "keywords": [
      "pagination",
      "page",
      "next",
      "previous",
      "current",
      "active"
    ]
  },
  {
    "style_id": 14,
    "title": "Alerts",
    "view_name": "alerts",
    "view_location": "/views/styles/alerts.html",
    "mod_date": "14 September, 2015",
    "keywords": [
      "alerts",
      "warning",
      "danger",
      "info",
      "success",
      "dismissible"
    ]
  },
  {
    "style_id": 16,
    "title": "Tooltips",
    "view_name": "tooltips",
    "view_location": "/views/styles/tooltips.html",
    "mod_date": "14 September, 2015",
    "keywords": [
      "tooltips"
    ]
  },
  {
    "style_id": 17,
    "title": "Accordions",
    "view_name": "accordions",
    "view_location": "/views/styles/accordions.html",
    "mod_date": "14 September, 2015",
    "keywords": [
      "accordions"
    ]
  },
  {
    "style_id": 18,    
    "title": "Tabs",
    "view_name": "tabs",
    "view_location": "/views/styles/tabs.html",
    "mod_date": "14 September, 2015",
    "keywords": [
      "tabs"
    ]
  },
  {
    "style_id": 19,    
    "title": "Modals",
    "view_name": "modals",
    "view_location": "/views/styles/modals.html",
    "mod_date": "14 September, 2015",
    "keywords": [
      "modals"
    ]
  }
]